[
  {
    "full_name": "williamfiset/Algorithms",
    "stargazers_count": 12097,
    "open_issues_count": 78,
    "forks_count": 3286
  },
  {
    "full_name": "careercup/CtCI-6th-Edition-JavaScript",
    "stargazers_count": 2577,
    "open_issues_count": 42,
    "forks_count": 1079
  },
  {
    "full_name": "npm/cli",
    "stargazers_count": 5573,
    "open_issues_count": 489,
    "forks_count": 1523
  },
  {
    "full_name": "airbnb/javascript",
    "stargazers_count": 120379,
    "open_issues_count": 137,
    "forks_count": 22971
  },
  {
    "full_name": "rubymorillo/pocket-tech-writing-list",
    "stargazers_count": 596,
    "open_issues_count": 0,
    "forks_count": 39
  },
  {
    "full_name": "streamich/react-use",
    "stargazers_count": 28331,
    "open_issues_count": 457,
    "forks_count": 2174
  },
  {
    "full_name": "bdougie/awesome-black-developers",
    "stargazers_count": 181,
    "open_issues_count": 1,
    "forks_count": 19
  },
  {
    "full_name": "30-seconds/30-seconds-of-code",
    "stargazers_count": 92717,
    "open_issues_count": 6,
    "forks_count": 9860
  },
  {
    "full_name": "lydiahallie/javascript-questions",
    "stargazers_count": 41836,
    "open_issues_count": 76,
    "forks_count": 5821
  },
  {
    "full_name": "ryanmcdermott/clean-code-javascript",
    "stargazers_count": 64761,
    "open_issues_count": 54,
    "forks_count": 8586
  },
  {
    "full_name": "goldbergyoni/nodebestpractices",
    "stargazers_count": 75552,
    "open_issues_count": 36,
    "forks_count": 7744
  },
  {
    "full_name": "public-apis/public-apis",
    "stargazers_count": 183015,
    "open_issues_count": 9,
    "forks_count": 21151
  },
  {
    "full_name": "sudheerj/javascript-interview-questions",
    "stargazers_count": 8526,
    "open_issues_count": 2,
    "forks_count": 2517
  },
  {
    "full_name": "Olshansk/interview",
    "stargazers_count": 15089,
    "open_issues_count": 6,
    "forks_count": 3422
  },
  {
    "full_name": "yangshun/tech-interview-handbook",
    "stargazers_count": 66859,
    "open_issues_count": 8,
    "forks_count": 9269
  },
  {
    "full_name": "DopplerHQ/awesome-interview-questions",
    "stargazers_count": 45302,
    "open_issues_count": 8,
    "forks_count": 6727
  },
  {
    "full_name": "jwasham/coding-interview-university",
    "stargazers_count": 211412,
    "open_issues_count": 45,
    "forks_count": 57336
  },
  {
    "full_name": "devpato/tech-podcasts-list",
    "stargazers_count": 68,
    "open_issues_count": 0,
    "forks_count": 6
  },
  {
    "full_name": "jordanliu/made-in-jamaica",
    "stargazers_count": 20,
    "open_issues_count": 1,
    "forks_count": 4
  },
  {
    "full_name": "typescript-cheatsheets/react",
    "stargazers_count": 31992,
    "open_issues_count": 2,
    "forks_count": 2682
  },
  {
    "full_name": "golang/go",
    "stargazers_count": 96079,
    "open_issues_count": 7639,
    "forks_count": 14363
  },
  {
    "full_name": "mattmakai/fullstackpython.com",
    "stargazers_count": 2686,
    "open_issues_count": 59,
    "forks_count": 606
  },
  {
    "full_name": "romenrg/evergreen-skills-developers",
    "stargazers_count": 1327,
    "open_issues_count": 1,
    "forks_count": 94
  },
  {
    "full_name": "PurpleBooth/a-good-readme-template",
    "stargazers_count": 294,
    "open_issues_count": 0,
    "forks_count": 248
  },
  {
    "full_name": "othneildrew/Best-README-Template",
    "stargazers_count": 5456,
    "open_issues_count": 9,
    "forks_count": 12756
  },
  {
    "full_name": "Virtual-Coffee/open-source",
    "stargazers_count": 20,
    "open_issues_count": 4,
    "forks_count": 4
  },
  {
    "full_name": "open-sauced/open-sauced",
    "stargazers_count": 595,
    "open_issues_count": 29,
    "forks_count": 194
  },
  {
    "full_name": "misterhtmlcss/twitter-todo-app",
    "stargazers_count": 2,
    "open_issues_count": 0,
    "forks_count": 2
  },
  {
    "full_name": "poliva/ggposrv",
    "stargazers_count": 127,
    "open_issues_count": 7,
    "forks_count": 40
  },
  {
    "full_name": "poliva/pyqtggpo",
    "stargazers_count": 127,
    "open_issues_count": 127,
    "forks_count": 53
  }
]